tushare_broke/__init__.py
tushare_broke-0.1.0.dist-info/METADATA
tushare_broke-0.1.0.dist-info/WHEEL
tushare_broke-0.1.0.dist-info/RECORD
